sqlitebiter/__init__.py
sqlitebiter/__main__.py
sqlitebiter/__version__.py
sqlitebiter/_common.py
sqlitebiter/_config.py
sqlitebiter/_const.py
sqlitebiter/_counter.py
sqlitebiter/_enum.py
sqlitebiter/_types.py
sqlitebiter/converter/__init__.py
sqlitebiter/converter/_base.py
sqlitebiter/converter/_common.py
sqlitebiter/converter/_dict_converter.py
sqlitebiter/converter/_file.py
sqlitebiter/converter/_gs.py
sqlitebiter/converter/_ipynb_converter.py
sqlitebiter/converter/_table_creator.py
sqlitebiter/converter/_text.py
sqlitebiter/converter/_url.py
sqlitebiter-0.36.3.dist-info/LICENSE
sqlitebiter-0.36.3.dist-info/METADATA
sqlitebiter-0.36.3.dist-info/WHEEL
sqlitebiter-0.36.3.dist-info/entry_points.txt
sqlitebiter-0.36.3.dist-info/top_level.txt
sqlitebiter-0.36.3.dist-info/RECORD
