Metadata-Version: 2.1
Name: sqlitebiter
Version: 0.36.3
Summary: sqlitebiter is a CLI tool to convert CSV / Excel / HTML / JSON / Jupyter Notebook / LDJSON / LTSV / Markdown / SQLite / SSV / TSV / Google-Sheets to a SQLite database file.
Home-page: https://github.com/thombashi/sqlitebiter
Author: Tsuyoshi Hombashi
Author-email: tsuyoshi.hombashi@gmail.com
License: MIT License
Project-URL: Changlog, https://github.com/thombashi/sqlitebiter/releases
Project-URL: Documentation, https://sqlitebiter.rtfd.io/
Project-URL: Download, https://github.com/thombashi/sqlitebiter/releases
Project-URL: Funding, https://github.com/sponsors/thombashi
Project-URL: Source, https://github.com/thombashi/sqlitebiter
Project-URL: Tracker, https://github.com/thombashi/sqlitebiter/issues
Keywords: SQLite,converter,CSV,Excel,Google Sheets,HTML,JSON,LTSV,TSV
Classifier: Development Status :: 4 - Beta
Classifier: Environment :: Console
Classifier: Framework :: Jupyter
Classifier: Intended Audience :: Information Technology
Classifier: License :: OSI Approved :: MIT License
Classifier: Operating System :: MacOS
Classifier: Operating System :: Microsoft
Classifier: Operating System :: Microsoft :: Windows
Classifier: Operating System :: POSIX
Classifier: Operating System :: POSIX :: Linux
Classifier: Programming Language :: Python :: 3
Classifier: Programming Language :: Python :: 3.7
Classifier: Programming Language :: Python :: 3.8
Classifier: Programming Language :: Python :: 3.9
Classifier: Programming Language :: Python :: 3.10
Classifier: Programming Language :: Python :: 3.11
Classifier: Programming Language :: Python :: 3.12
Classifier: Programming Language :: Python :: 3 :: Only
Classifier: Topic :: Database
Requires-Python: >=3.7
License-File: LICENSE
Requires-Dist: appconfigpy<3,>=1.0.1
Requires-Dist: click<9,>=6.2
Requires-Dist: envinfopy<1,>=0.0.7
Requires-Dist: loguru<1,>=0.4.1
Requires-Dist: msgfy<1,>=0.1.0
Requires-Dist: nbformat<6,>=4.4.0
Requires-Dist: path<17,>=13
Requires-Dist: pathvalidate<4,>=2.5.2
Requires-Dist: pytablereader[excel,md,sqlite,url]<2,>=0.31.3
Requires-Dist: retryrequests<1,>=0.0.2
Requires-Dist: SimpleSQLite!=1.5.0,!=1.5.1,<2,>=1.3.2
Requires-Dist: tcolorpy<1,>=0.0.5
Requires-Dist: typepy<2,>=1.2.0
Provides-Extra: all
Requires-Dist: gspread; extra == "all"
Requires-Dist: oauth2client; extra == "all"
Requires-Dist: pyOpenSSL; extra == "all"
Requires-Dist: pypandoc; extra == "all"
Requires-Dist: ujson<6,>=1.33; extra == "all"
Provides-Extra: buildexe
Requires-Dist: pyinstaller>=5.13; extra == "buildexe"
Provides-Extra: docs
Requires-Dist: sphinx_rtd_theme>=1.2.2; extra == "docs"
Requires-Dist: Sphinx>=2.4; extra == "docs"
Requires-Dist: gspread; extra == "docs"
Requires-Dist: oauth2client; extra == "docs"
Requires-Dist: pyOpenSSL; extra == "docs"
Requires-Dist: pypandoc; extra == "docs"
Requires-Dist: ujson<6,>=1.33; extra == "docs"
Provides-Extra: gs
Requires-Dist: gspread; extra == "gs"
Requires-Dist: oauth2client; extra == "gs"
Requires-Dist: pyOpenSSL; extra == "gs"
Provides-Extra: mediawiki
Requires-Dist: pypandoc; extra == "mediawiki"
Provides-Extra: test
Requires-Dist: XlsxWriter>=3; extra == "test"
Requires-Dist: sqliteschema[dumps]>=1.3; extra == "test"
Requires-Dist: pytest>=7; extra == "test"
Requires-Dist: responses>=0.23; extra == "test"
Requires-Dist: nbformat>=5.0.6; extra == "test"
Requires-Dist: gspread; extra == "test"
Requires-Dist: ujson<6,>=1.33; extra == "test"
Requires-Dist: pypandoc; extra == "test"
Requires-Dist: pytest-md-report>=0.5; extra == "test"
Requires-Dist: pytest-discord>=0.1.6; extra == "test"
Requires-Dist: pyOpenSSL; extra == "test"
Requires-Dist: oauth2client; extra == "test"
